XX/BloomFilter.py
XX/BuiltinFunctions.py
XX/Debug.py
XX/UpgradeAllPackage.py
XX/__init__.py
XX/configs.py
XX/funclib.py
XX/DB/HBaseHelper.py
XX/DB/HappyBaseHelper.py
XX/DB/Helper.py
XX/DB/MongoHelper.py
XX/DB/MysqlHelper.py
XX/DB/MysqlPoolHelper.py
XX/DB/RedisHelper.py
XX/DB/SqlAlchemyHelper.py
XX/DB/__init__.py
XX/Date/DatetimeHelper.py
XX/Date/__init__.py
XX/Decorator/Decorator.py
XX/Decorator/ExceptionDecorator.py
XX/Decorator/__init__.py
XX/Decorator/Scrapy/JsonDecorator.py
XX/Decorator/Scrapy/__init__.py
XX/Dict/DictHelper.py
XX/Dict/__init__.py
XX/ETL/Mysql2Redis.py
XX/ETL/__init__.py
XX/Encrypt/EncryptHelper.py
XX/Encrypt/__init__.py
XX/File/FileHelper.py
XX/File/RootPath.py
XX/File/__init__.py
XX/HBase/CacheHelper.py
XX/HBase/DMHelper.py
XX/HBase/__init__.py
XX/HTML/HeaderHelper.py
XX/HTML/HtmlHelper.py
XX/HTML/JSHTML.py
XX/HTML/UrlHelper.py
XX/HTML/UrlInfoHelper.py
XX/HTML/__init__.py
XX/HTML/html_to_article.py
XX/HTML/Parse/NewsParse.py
XX/HTML/Parse/__init__.py
XX/HTTP/IPHelper.py
XX/HTTP/Proxy.py
XX/HTTP/RequestsHelper.py
XX/HTTP/__init__.py
XX/Hive/Helper.py
XX/Hive/__init__.py
XX/Img/__init__.py
XX/Json/DateEncode.py
XX/Json/__init__.py
XX/List/ListHelper.py
XX/List/__init__.py
XX/Model/__init__.py
XX/Model/Items/BBSItem.py
XX/Model/Items/BaiduSearchResultItem.py
XX/Model/Items/GPNewsItem.py
XX/Model/Items/Meihua.py
XX/Model/Items/NewsItem.py
XX/Model/Items/PostItem.py
XX/Model/Items/PostReviewCount.py
XX/Model/Items/__init__.py
XX/Model/MongoEngine/__init__.py
XX/Model/Object/CrawlerUrl.py
XX/Model/Object/ResponseJson.py
XX/Model/Object/ResponseObj.py
XX/Model/Object/__init__.py
XX/Model/SqlAlchemy/BaseModel.py
XX/Model/SqlAlchemy/SaaSModel.py
XX/Model/SqlAlchemy/T.py
XX/Model/SqlAlchemy/ZhihuModel.py
XX/Model/SqlAlchemy/__init__.py
XX/Model/SqlAlchemy/Aiweibang/CountInfo.py
XX/Model/SqlAlchemy/Aiweibang/ReadNum.py
XX/Model/SqlAlchemy/Aiweibang/WxCount.py
XX/Model/SqlAlchemy/Aiweibang/__init__.py
XX/Model/SqlAlchemy/Company/BossDetail.py
XX-3.3.1.dist-info/METADATA
XX-3.3.1.dist-info/WHEEL
XX-3.3.1.dist-info/top_level.txt
XX-3.3.1.dist-info/RECORD
